{
  "f8e6b000-5643-4b86-9080-aa680ce1f599": {
    "asset": 1507880085000,
    "meta": 1507880085000,
    "relativePath": "image"
  },
  "e851e89b-faa2-4484-bea6-5c01dd9f06e2": {
    "asset": 1507880085000,
    "meta": 1508395657329,
    "relativePath": "image/default_btn_normal.png"
  },
  "71561142-4c83-4933-afca-cb7a17f67053": {
    "asset": 1507880085000,
    "meta": 1508395657326,
    "relativePath": "image/default_btn_disabled.png"
  },
  "b43ff3c2-02bb-4874-81f7-f2dea6970f18": {
    "asset": 1507880085000,
    "meta": 1508395657343,
    "relativePath": "image/default_btn_pressed.png"
  },
  "d81ec8ad-247c-4e62-aa3c-d35c4193c7af": {
    "asset": 1507880085000,
    "meta": 1508395657342,
    "relativePath": "image/default_panel.png"
  },
  "99170b0b-d210-46f1-b213-7d9e3f23098a": {
    "asset": 1507880085000,
    "meta": 1508395657356,
    "relativePath": "image/default_progressbar_bg.png"
  },
  "cfef78f1-c8df-49b7-8ed0-4c953ace2621": {
    "asset": 1507880085000,
    "meta": 1508395657359,
    "relativePath": "image/default_progressbar.png"
  },
  "567dcd80-8bf4-4535-8a5a-313f1caf078a": {
    "asset": 1507880085000,
    "meta": 1508395657365,
    "relativePath": "image/default_radio_button_off.png"
  },
  "9d60001f-b5f4-4726-a629-2659e3ded0b8": {
    "asset": 1507880085000,
    "meta": 1508395657370,
    "relativePath": "image/default_radio_button_on.png"
  },
  "4bab67cb-18e6-4099-b840-355f0473f890": {
    "asset": 1507880085000,
    "meta": 1508395657375,
    "relativePath": "image/default_scrollbar_bg.png"
  },
  "617323dd-11f4-4dd3-8eec-0caf6b3b45b9": {
    "asset": 1507880085000,
    "meta": 1508395657385,
    "relativePath": "image/default_scrollbar_vertical_bg.png"
  },
  "0291c134-b3da-4098-b7b5-e397edbe947f": {
    "asset": 1507880085000,
    "meta": 1508395657398,
    "relativePath": "image/default_scrollbar.png"
  },
  "d6d3ca85-4681-47c1-b5dd-d036a9d39ea2": {
    "asset": 1507880085000,
    "meta": 1508395657391,
    "relativePath": "image/default_scrollbar_vertical.png"
  },
  "6e056173-d285-473c-b206-40a7fff5386e": {
    "asset": 1507880085000,
    "meta": 1508395657411,
    "relativePath": "image/default_sprite.png"
  },
  "73a0903d-d80e-4e3c-aa67-f999543c08f5": {
    "asset": 1507880085000,
    "meta": 1508395657413,
    "relativePath": "image/default_toggle_checkmark.png"
  },
  "0275e94c-56a7-410f-bd1a-fc7483f7d14a": {
    "asset": 1507880085000,
    "meta": 1508395657400,
    "relativePath": "image/default_sprite_splash.png"
  },
  "c25b9d50-c8fc-4d27-beeb-6e7c1f2e5c0f": {
    "asset": 1507880085000,
    "meta": 1508395657423,
    "relativePath": "image/default_toggle_disabled.png"
  },
  "b181c1e4-0a72-4a91-bfb0-ae6f36ca60bd": {
    "asset": 1507880085000,
    "meta": 1508395657434,
    "relativePath": "image/default_toggle_pressed.png"
  },
  "fc09f9bd-2cce-4605-b630-8145ef809ed6": {
    "asset": 1507880085000,
    "meta": 1507880085000,
    "relativePath": "misc"
  },
  "d29077ba-1627-4a72-9579-7b56a235340c": {
    "asset": 1507880085000,
    "meta": 1508395657428,
    "relativePath": "image/default_toggle_normal.png"
  },
  "2be36297-9abb-4fee-8049-9ed5e271da8a": {
    "asset": 1507880085000,
    "meta": 1507880085000,
    "relativePath": "misc/default_video.mp4"
  },
  "f6e6dd15-71d1-4ffe-ace7-24fd39942c05": {
    "asset": 1507880085000,
    "meta": 1507880085000,
    "relativePath": "obsolete"
  },
  "b8223619-7e38-47c4-841f-9160c232495a": {
    "asset": 1507880085000,
    "meta": 1507880085000,
    "relativePath": "obsolete/atom.plist"
  },
  "f743d2b6-b7ea-4c14-a55b-547ed4d0a045": {
    "asset": 1507880085000,
    "meta": 1507880085000,
    "relativePath": "particle"
  },
  "b2687ac4-099e-403c-a192-ff477686f4f5": {
    "asset": 1507880085000,
    "meta": 1507880085000,
    "relativePath": "particle/atom.plist"
  },
  "ae6c6c98-11e4-452f-8758-75f5c6a56e83": {
    "asset": 1507880085000,
    "meta": 1507880085000,
    "relativePath": "prefab"
  },
  "972b9a4d-47ee-4c74-b5c3-61d8a69bc29f": {
    "asset": 1507880085000,
    "meta": 1508395657442,
    "relativePath": "prefab/button.prefab"
  },
  "2c937608-2562-40ea-b264-7395df6f0cea": {
    "asset": 1507880085000,
    "meta": 1508395657444,
    "relativePath": "prefab/canvas.prefab"
  },
  "61aeb05b-3b32-452b-8eed-2b76deeed554": {
    "asset": 1507880085000,
    "meta": 1508395657445,
    "relativePath": "prefab/editbox.prefab"
  },
  "27756ebb-3d33-44b0-9b96-e858fadd4dd4": {
    "asset": 1507880085000,
    "meta": 1508395657446,
    "relativePath": "prefab/label.prefab"
  },
  "785a442c-3ceb-45be-a46e-7317f625f3b9": {
    "asset": 1507880085000,
    "meta": 1508395657447,
    "relativePath": "prefab/layout.prefab"
  },
  "ca8401fe-ad6e-41a8-bd46-8e3e4e9945be": {
    "asset": 1507880085000,
    "meta": 1508395657448,
    "relativePath": "prefab/pageview.prefab"
  },
  "cd33edea-55f5-46c2-958d-357a01384a36": {
    "asset": 1507880085000,
    "meta": 1508395657450,
    "relativePath": "prefab/particlesystem.prefab"
  },
  "5965ffac-69da-4b55-bcde-9225d0613c28": {
    "asset": 1507880085000,
    "meta": 1508395657452,
    "relativePath": "prefab/progressBar.prefab"
  },
  "4a37dd57-78cd-4cec-aad4-f11a73d12b63": {
    "asset": 1507880085000,
    "meta": 1508395657454,
    "relativePath": "prefab/richtext.prefab"
  },
  "32044bd2-481f-4cf1-a656-e2b2fb1594eb": {
    "asset": 1507880085000,
    "meta": 1508395657456,
    "relativePath": "prefab/scrollview.prefab"
  },
  "1f55e3be-b89b-4b79-88de-47fd31018044": {
    "asset": 1507880085000,
    "meta": 1508395657460,
    "relativePath": "prefab/sprite_splash.prefab"
  },
  "0004d1cf-a0ad-47d8-ab17-34d3db9d35a3": {
    "asset": 1507880085000,
    "meta": 1508395657458,
    "relativePath": "prefab/slider.prefab"
  },
  "96083d03-c332-4a3f-9386-d03e2d19e8ee": {
    "asset": 1507880085000,
    "meta": 1508395657461,
    "relativePath": "prefab/sprite.prefab"
  },
  "7de03a80-4457-438d-95a7-3e7cdffd6086": {
    "asset": 1507880085000,
    "meta": 1508395657462,
    "relativePath": "prefab/tiledmap.prefab"
  },
  "0d784963-d024-4ea6-a7db-03be0ad63010": {
    "asset": 1507880085000,
    "meta": 1508395657463,
    "relativePath": "prefab/toggle.prefab"
  },
  "bf0a434c-84dd-4a8e-a08a-7a36f180cc75": {
    "asset": 1507880085000,
    "meta": 1508395657466,
    "relativePath": "prefab/toggleGroup.prefab"
  },
  "232d2782-c4bd-4bb4-9e01-909f03d6d3b9": {
    "asset": 1507880085000,
    "meta": 1508395657467,
    "relativePath": "prefab/videoplayer.prefab"
  },
  "8c5001fd-07ee-4a4b-a8a0-63e15195e94d": {
    "asset": 1507880085000,
    "meta": 1508395657469,
    "relativePath": "prefab/webview.prefab"
  },
  "817f3009-1a54-4a5a-a6e9-813bd86d362c": {
    "asset": 1509876218900,
    "meta": 1508375889877,
    "relativePath": "image"
  },
  "f6c45d85-c408-4da0-924d-c9c087ee2a95": {
    "asset": 1489468962000,
    "meta": 1491444037000,
    "relativePath": "image/a10.jpg"
  },
  "75fadf26-ad09-49e4-9253-963d4acd64c6": {
    "asset": 1489468962000,
    "meta": 1491444037000,
    "relativePath": "image/a1.jpg"
  },
  "311cdaeb-44c0-4230-8805-0c19228c0604": {
    "asset": 1489468962000,
    "meta": 1491444038000,
    "relativePath": "image/a11.jpg"
  },
  "52c15a79-76b5-4c8e-8e0b-a910cb86c1e4": {
    "asset": 1489468962000,
    "meta": 1491444038000,
    "relativePath": "image/a12.jpg"
  },
  "b2347a13-fd56-46c5-8152-ec0cf98e41a7": {
    "asset": 1489468962000,
    "meta": 1491444038000,
    "relativePath": "image/a2.jpg"
  },
  "c98545c3-ac62-4658-93c3-522328b08685": {
    "asset": 1489468962000,
    "meta": 1491444038000,
    "relativePath": "image/a13.jpg"
  },
  "78b03edc-70d9-4c4a-a163-60cf01396e06": {
    "asset": 1489468962000,
    "meta": 1491444038000,
    "relativePath": "image/a3.jpg"
  },
  "91ee87fa-d1d2-48b4-9969-88cd5e7a4878": {
    "asset": 1489468962000,
    "meta": 1491444038000,
    "relativePath": "image/a4.jpg"
  },
  "b1bfc70d-db51-487b-9d33-8ce076392c00": {
    "asset": 1489468962000,
    "meta": 1491444038000,
    "relativePath": "image/a5.jpg"
  },
  "d10d12e7-ec38-4be9-a7c5-9a34bf19ae45": {
    "asset": 1489468962000,
    "meta": 1491444038000,
    "relativePath": "image/a6.jpg"
  },
  "7ca9f4f6-c36e-4d10-8fec-a098f08b97a2": {
    "asset": 1489468962000,
    "meta": 1491444038000,
    "relativePath": "image/a8.jpg"
  },
  "3250586e-e064-4fdd-9286-64ae599a7d24": {
    "asset": 1489468962000,
    "meta": 1491444038000,
    "relativePath": "image/a7.jpg"
  },
  "8c994ed3-be9d-4876-8b5e-dbe5314088c0": {
    "asset": 1489468962000,
    "meta": 1491444038000,
    "relativePath": "image/a9.jpg"
  },
  "7d9cf337-4d2e-4d6f-aa6e-937fbd6a6388": {
    "asset": 1489468962000,
    "meta": 1491444038000,
    "relativePath": "image/b1.jpg"
  },
  "05e3e416-1cc8-49a2-93cf-ffed63078ed4": {
    "asset": 1489468962000,
    "meta": 1491444038000,
    "relativePath": "image/b10.jpg"
  },
  "c9b75f26-3d6f-4ff2-8ef9-2c9fb9a2b02c": {
    "asset": 1489468962000,
    "meta": 1491444038000,
    "relativePath": "image/b11.jpg"
  },
  "f6247f86-7324-4285-ab63-5d1801d72caa": {
    "asset": 1489468962000,
    "meta": 1491444038000,
    "relativePath": "image/b12.jpg"
  },
  "fb2331a5-a551-444c-acb6-b622f2af95d6": {
    "asset": 1489468962000,
    "meta": 1491444038000,
    "relativePath": "image/b13.jpg"
  },
  "9db6a2a1-b403-4315-9c8f-fbb747490918": {
    "asset": 1489468962000,
    "meta": 1491444038000,
    "relativePath": "image/b2.jpg"
  },
  "398cc78d-5a9f-4fbd-b186-ce7b60206dc8": {
    "asset": 1489468962000,
    "meta": 1491444038000,
    "relativePath": "image/b3.jpg"
  },
  "7dcfbf18-5425-4fa1-a66e-79225fa819cc": {
    "asset": 1489468962000,
    "meta": 1491444038000,
    "relativePath": "image/b4.jpg"
  },
  "0b73069c-ac0b-4549-9d25-072aa449a48a": {
    "asset": 1489468962000,
    "meta": 1491444038000,
    "relativePath": "image/b5.jpg"
  },
  "051d5a13-b7e4-443c-b721-40c023f1bf55": {
    "asset": 1489468962000,
    "meta": 1491444038000,
    "relativePath": "image/b6.jpg"
  },
  "9a9c4d77-4606-43bf-b401-71da33b843cf": {
    "asset": 1489468962000,
    "meta": 1491444038000,
    "relativePath": "image/b7.jpg"
  },
  "2518f1c8-7cda-47bf-af60-6064d93d3ba9": {
    "asset": 1489468962000,
    "meta": 1491444038000,
    "relativePath": "image/b8.jpg"
  },
  "ded4b9a9-4ab5-4b71-aaba-2862cc044a3f": {
    "asset": 1489468962000,
    "meta": 1491444038000,
    "relativePath": "image/b9.jpg"
  },
  "236810ab-de6f-4482-a389-160b7a86889f": {
    "asset": 1489468962000,
    "meta": 1491444038000,
    "relativePath": "image/c1.jpg"
  },
  "d3a73ca7-3894-4014-b968-10b805bb781b": {
    "asset": 1490337582000,
    "meta": 1491444038000,
    "relativePath": "image/bg.jpg"
  },
  "2e0e842d-f91f-41b1-b66a-5f112eb6fc09": {
    "asset": 1489468962000,
    "meta": 1491444038000,
    "relativePath": "image/c10.jpg"
  },
  "98301b21-7365-41da-b9df-4089e08978ff": {
    "asset": 1489468962000,
    "meta": 1491444038000,
    "relativePath": "image/c11.jpg"
  },
  "0e4a8f34-4a51-4ae8-b021-fcda675bdc60": {
    "asset": 1489468962000,
    "meta": 1491444038000,
    "relativePath": "image/c12.jpg"
  },
  "678a7b94-9cc8-44a7-9874-8a73235fc1f4": {
    "asset": 1489468962000,
    "meta": 1491444038000,
    "relativePath": "image/c13.jpg"
  },
  "34050e3c-461a-4a3e-bd4a-a487a9cfdfb3": {
    "asset": 1489468962000,
    "meta": 1491444038000,
    "relativePath": "image/c2.jpg"
  },
  "a51c3af0-3a09-434b-ac58-c3f54ee59594": {
    "asset": 1489468962000,
    "meta": 1491444038000,
    "relativePath": "image/c3.jpg"
  },
  "48377872-601f-4eed-95d0-fe3ce92d8b6b": {
    "asset": 1489468962000,
    "meta": 1491444038000,
    "relativePath": "image/c4.jpg"
  },
  "805aad21-462a-4c00-97a6-3df244604c41": {
    "asset": 1489468962000,
    "meta": 1491444038000,
    "relativePath": "image/c6.jpg"
  },
  "7b3d0d27-0b3a-40e3-b4e6-7804ef4ab5fd": {
    "asset": 1489468962000,
    "meta": 1491444038000,
    "relativePath": "image/c5.jpg"
  },
  "7f1be5c1-6828-46df-9355-12c20f684bda": {
    "asset": 1489468962000,
    "meta": 1491444038000,
    "relativePath": "image/c7.jpg"
  },
  "5ca53589-7993-46da-9f77-7b60163d7a87": {
    "asset": 1489468962000,
    "meta": 1491444038000,
    "relativePath": "image/c8.jpg"
  },
  "f52c1e83-0d43-4ada-9e5e-536770b0ddc4": {
    "asset": 1489468962000,
    "meta": 1491444038000,
    "relativePath": "image/c9.jpg"
  },
  "60957672-3ebf-4415-af5a-f3bbad5d5908": {
    "asset": 1489468962000,
    "meta": 1491444038000,
    "relativePath": "image/d1.jpg"
  },
  "eb2cffcb-dfeb-494e-8253-072d997694cd": {
    "asset": 1489468962000,
    "meta": 1491444038000,
    "relativePath": "image/d11.jpg"
  },
  "9c7f3352-e7e6-4ed9-b171-43ee9babb819": {
    "asset": 1489468962000,
    "meta": 1491444038000,
    "relativePath": "image/d10.jpg"
  },
  "dcbe44b8-4bf5-4ddd-a13e-04b862862905": {
    "asset": 1489468962000,
    "meta": 1491444038000,
    "relativePath": "image/d13.jpg"
  },
  "9a94e9b8-3b11-4aa5-860c-f4575f5d9406": {
    "asset": 1489468962000,
    "meta": 1491444038000,
    "relativePath": "image/d12.jpg"
  },
  "019f3867-362b-4bd5-9f09-c79bce53518b": {
    "asset": 1489468962000,
    "meta": 1491444038000,
    "relativePath": "image/d3.jpg"
  },
  "1e075c56-2254-4e34-b0a8-5273176c0504": {
    "asset": 1489468962000,
    "meta": 1491444038000,
    "relativePath": "image/d2.jpg"
  },
  "712dda97-7fa3-42f0-966b-e3ae62898d1a": {
    "asset": 1489468962000,
    "meta": 1491444038000,
    "relativePath": "image/d4.jpg"
  },
  "a5e498f9-1a61-4683-9c5a-46fb67b3782e": {
    "asset": 1489468962000,
    "meta": 1491444038000,
    "relativePath": "image/d5.jpg"
  },
  "eedad8bd-bcf1-4458-b0d7-26eb547cc903": {
    "asset": 1489468962000,
    "meta": 1491444038000,
    "relativePath": "image/d7.jpg"
  },
  "f475dc0d-b433-442b-8fc0-f70d2d1d7593": {
    "asset": 1489468962000,
    "meta": 1491444038000,
    "relativePath": "image/d6.jpg"
  },
  "ca889cb4-1dfa-4696-a7ec-687cbf093258": {
    "asset": 1489468962000,
    "meta": 1491444038000,
    "relativePath": "image/d8.jpg"
  },
  "215475f4-574f-4fff-ae33-40380b03f663": {
    "asset": 1489468962000,
    "meta": 1491444038000,
    "relativePath": "image/d9.jpg"
  },
  "4f9222a3-0b9e-416e-b427-c65e94f6e18d": {
    "asset": 1490681505000,
    "meta": 1491444038000,
    "relativePath": "image/E0.jpg"
  },
  "ea1b68ae-4991-4f41-9d78-178eeee7e6da": {
    "asset": 1490681505000,
    "meta": 1491444038000,
    "relativePath": "image/E1.jpg"
  },
  "b0cb47b4-9cd0-47cc-ada3-3c1383744923": {
    "asset": 1510655625039,
    "meta": 1510655625052,
    "relativePath": "main.fire"
  },
  "48c53c8a-051e-406b-a362-50921e526cfa": {
    "asset": 1490836562000,
    "meta": 1491444038000,
    "relativePath": "Prefab"
  },
  "aa927d89-b4bc-48c1-9b23-4712998d057f": {
    "asset": 1490339497000,
    "meta": 1491444038000,
    "relativePath": "Prefab/a1.prefab"
  },
  "49bd03d7-83bd-490d-8f76-eb7ebdbe83c5": {
    "asset": 1490339473000,
    "meta": 1491444038000,
    "relativePath": "Prefab/a10.prefab"
  },
  "f8ffa315-c48e-41be-a6c3-9f79dd6baf70": {
    "asset": 1490339485000,
    "meta": 1491444038000,
    "relativePath": "Prefab/a11.prefab"
  },
  "a84a9831-8a98-4015-a9d1-fd2d4f425936": {
    "asset": 1490339482000,
    "meta": 1491444038000,
    "relativePath": "Prefab/a12.prefab"
  },
  "864d618a-3dd3-48cc-99e0-1d1515dad2d9": {
    "asset": 1490339490000,
    "meta": 1491444038000,
    "relativePath": "Prefab/a13.prefab"
  },
  "df49ec6c-8a1a-45cf-a1f5-5195d1f530ba": {
    "asset": 1490339494000,
    "meta": 1491444038000,
    "relativePath": "Prefab/a2.prefab"
  },
  "9854527a-1c68-4525-bff6-3a0100b9b625": {
    "asset": 1490339502000,
    "meta": 1491444038000,
    "relativePath": "Prefab/a5.prefab"
  },
  "ef7ee664-2d94-4460-b57e-548fe1b387af": {
    "asset": 1490339499000,
    "meta": 1491444038000,
    "relativePath": "Prefab/a3.prefab"
  },
  "b7cc390c-e9dc-43f4-a4b4-037863015630": {
    "asset": 1490339525000,
    "meta": 1491444038000,
    "relativePath": "Prefab/b1.prefab"
  },
  "19f8dc96-be0c-410a-8b60-c72c7d350984": {
    "asset": 1490339530000,
    "meta": 1491444038000,
    "relativePath": "Prefab/b10.prefab"
  },
  "754a602f-d8c3-49f1-a63c-446b9b3ae10d": {
    "asset": 1490339508000,
    "meta": 1491444038000,
    "relativePath": "Prefab/b11.prefab"
  },
  "e1f9ce60-cfbc-422f-b9a8-986a84bb448e": {
    "asset": 1490339511000,
    "meta": 1491444038000,
    "relativePath": "Prefab/b12.prefab"
  },
  "858aef53-5d1b-4931-8c45-f4a6e78abe5c": {
    "asset": 1490339515000,
    "meta": 1491444038000,
    "relativePath": "Prefab/b13.prefab"
  },
  "91f1028e-b74e-4730-ac16-f56514edc53d": {
    "asset": 1490339537000,
    "meta": 1491444038000,
    "relativePath": "Prefab/b2.prefab"
  },
  "5d7bf215-379c-47c4-a236-b22dbc8f1a08": {
    "asset": 1490339541000,
    "meta": 1491444038000,
    "relativePath": "Prefab/b3.prefab"
  },
  "de526bdb-6ce7-4530-b268-b0dec811a556": {
    "asset": 1490339535000,
    "meta": 1491444038000,
    "relativePath": "Prefab/b5.prefab"
  },
  "0759dcdf-b902-4880-85bb-ada156dbb7fb": {
    "asset": 1490339545000,
    "meta": 1491444038000,
    "relativePath": "Prefab/bg.prefab"
  },
  "8d028a7d-18cb-4582-87f8-48496f6c7ff3": {
    "asset": 1490339554000,
    "meta": 1491444038000,
    "relativePath": "Prefab/c1.prefab"
  },
  "49c7a772-1e5d-475f-81f5-a3fee7460b73": {
    "asset": 1490339552000,
    "meta": 1491444038000,
    "relativePath": "Prefab/c10.prefab"
  },
  "cdf39919-010e-48da-8b20-8a3a035c614f": {
    "asset": 1490339550000,
    "meta": 1491444038000,
    "relativePath": "Prefab/c11.prefab"
  },
  "d71f439e-6df6-4488-a341-c724f9b5fd31": {
    "asset": 1490339544000,
    "meta": 1491444038000,
    "relativePath": "Prefab/c12.prefab"
  },
  "e00aba95-a6a1-481b-bf36-4b64062453d8": {
    "asset": 1490339556000,
    "meta": 1491444038000,
    "relativePath": "Prefab/c13.prefab"
  },
  "ae23ea64-992c-4418-9070-8d9c8b3d7390": {
    "asset": 1490339547000,
    "meta": 1491444038000,
    "relativePath": "Prefab/c2.prefab"
  },
  "f3c962c3-32cd-44b0-bbaf-c86c2f57e7be": {
    "asset": 1490339559000,
    "meta": 1491444038000,
    "relativePath": "Prefab/c3.prefab"
  },
  "00ce5e44-9d72-4a29-aac5-ed782f767283": {
    "asset": 1490339569000,
    "meta": 1491444038000,
    "relativePath": "Prefab/d1.prefab"
  },
  "8a3424fe-f1ae-4e24-8d97-67c18374a15a": {
    "asset": 1490339560000,
    "meta": 1491444038000,
    "relativePath": "Prefab/c5.prefab"
  },
  "e036507a-8a56-4597-955f-905cdc9208d5": {
    "asset": 1490339564000,
    "meta": 1491444038000,
    "relativePath": "Prefab/d10.prefab"
  },
  "c96e7c05-6472-40d4-9ce4-581273ddd869": {
    "asset": 1490339566000,
    "meta": 1491444038000,
    "relativePath": "Prefab/d11.prefab"
  },
  "7a06b00c-0c1c-4cd0-b8ff-549f0e2e602e": {
    "asset": 1490339568000,
    "meta": 1491444038000,
    "relativePath": "Prefab/d12.prefab"
  },
  "65753993-2b8d-4641-aaed-afddf09be0e9": {
    "asset": 1490339571000,
    "meta": 1491444038000,
    "relativePath": "Prefab/d13.prefab"
  },
  "2d3c7413-732c-476c-80ef-e627c620b665": {
    "asset": 1490339572000,
    "meta": 1491444038000,
    "relativePath": "Prefab/d2.prefab"
  },
  "7789e8ee-7da3-4cf2-8417-77ccbe3c7e00": {
    "asset": 1490339574000,
    "meta": 1491444038000,
    "relativePath": "Prefab/d3.prefab"
  },
  "a16a5775-5773-468d-a3fc-8d45b16e4910": {
    "asset": 1491018680000,
    "meta": 1491444038000,
    "relativePath": "Prefab/E0.prefab"
  },
  "1ca17342-cc60-48b5-b253-ebefa4f58ee5": {
    "asset": 1490339575000,
    "meta": 1491444038000,
    "relativePath": "Prefab/d5.prefab"
  },
  "bffc9bda-0b30-43c3-aa1f-e8e767b96bac": {
    "asset": 1490682072000,
    "meta": 1491444038000,
    "relativePath": "Prefab/E1.prefab"
  },
  "8956b91a-e4ad-471a-b691-1b3fd0289970": {
    "asset": 1510644433008,
    "meta": 1508375889880,
    "relativePath": "script"
  },
  "1a212458-ec86-48fb-af20-e2e55a5e5b76": {
    "asset": 1509876390979,
    "meta": 1509876390984,
    "relativePath": "Prefab/Player.prefab"
  },
  "88fd022e-c0d7-410d-9016-280bfb6ca5fb": {
    "asset": 1490836562000,
    "meta": 1491444038000,
    "relativePath": "image/run.png"
  },
  "b3ac12b2-a95f-4757-be0e-31748a995cca": {
    "asset": 1491036714000,
    "meta": 1508395658825,
    "relativePath": "script/PaiAn.js"
  },
  "3865c36f-a337-4207-ad79-0cdf17f79c74": {
    "asset": 1491038336000,
    "meta": 1508395658589,
    "relativePath": "script/AI.js"
  },
  "8c5d841a-9811-41b9-a1d9-8ed40151ca7e": {
    "asset": 1491542096000,
    "meta": 1508395658832,
    "relativePath": "script/Player.js"
  },
  "a1f63068-95a2-4d7d-b227-7d12bd7f984b": {
    "asset": 1509872201822,
    "meta": 1509872201890,
    "relativePath": "launch.fire"
  },
  "5ffe2a91-d15c-4d58-937f-98323e6a00dc": {
    "asset": 1509872532045,
    "meta": 1509872532064,
    "relativePath": "info.fire"
  },
  "9cac7d0e-608e-4aee-a57c-b1af15c81452": {
    "asset": 1506755018000,
    "meta": 1508395658804,
    "relativePath": "script/Launch.js"
  },
  "260eb6b6-f2e5-4009-a252-7355f68f460a": {
    "asset": 1506755324000,
    "meta": 1508395658711,
    "relativePath": "script/Info.js"
  },
  "4e9e00fa-f116-48f2-890f-be5630ca8a93": {
    "asset": 1506759404000,
    "meta": 1506759404000,
    "relativePath": "image/info.jpg"
  },
  "af267f8e-bcce-485a-9af6-034bbedede6f": {
    "asset": 1506761224000,
    "meta": 1506761224000,
    "relativePath": "image/zhuoan.jpg"
  },
  "31f33ec8-2da9-46b2-ab06-2fcab4219321": {
    "asset": 1506763110000,
    "meta": 1506763110000,
    "relativePath": "image/launch.jpg"
  },
  "83e6ce94-888c-4719-a2de-170f68cd7e71": {
    "asset": 1509876194736,
    "meta": 1509876218917,
    "relativePath": "image/default_head.png"
  },
  "d62f154b-56ec-4fd6-aa4e-4fb37568bf0d": {
    "asset": 1510646626635,
    "meta": 1510646384923,
    "relativePath": "resources/language"
  },
  "478be486-eb4c-4989-81e5-0eef805b004e": {
    "asset": 1510647810779,
    "meta": 1510646626635,
    "relativePath": "resources/language/string_cn.json"
  },
  "b74aafbf-3f99-49e1-9318-c2d6cee5dc11": {
    "asset": 1510651092878,
    "meta": 1510651070800,
    "relativePath": "resources"
  },
  "166cff7e-dd80-4991-82eb-342f42a8cc9a": {
    "asset": 1510652727349,
    "meta": 1510652628745,
    "relativePath": "resources/language/string_eng.json"
  },
  "2ce3d6a3-cfcd-450d-a8c3-3e1e9c17af71": {
    "asset": 1510655080326,
    "meta": 1510655101638,
    "relativePath": "script/Common.js"
  },
  "52296b58-78e2-46b6-8c87-b469358c5ba9": {
    "asset": 1510655597000,
    "meta": 1510655611885,
    "relativePath": "script/Game.js"
  },
  "875aaf14-cf66-4414-9582-300c8bbce244": {
    "asset": 1510655180000,
    "meta": 1510655611886,
    "relativePath": "script/Language.js"
  }
}